<?xml version="1.0" encoding="utf-8" ?>
<dwsync>
<file name="action.png" server="ftp.sffscorpion.com//" local="132122270370000000" remote="-1" Dst="-1" />
<file name="airing-today.png" server="ftp.sffscorpion.com//" local="132122565660000000" remote="-1" Dst="-1" />
<file name="bann.png" server="ftp.sffscorpion.com//" local="132122274770000000" remote="-1" Dst="-1" />
<file name="banner.png" server="ftp.sffscorpion.com//" local="132122565660000000" remote="-1" Dst="-1" />
<file name="box-office.png" server="ftp.sffscorpion.com//" local="132122565660000000" remote="-1" Dst="-1" />
<file name="boxsets.png" server="ftp.sffscorpion.com//" local="132122565660000000" remote="-1" Dst="-1" />
<file name="calendar.png" server="ftp.sffscorpion.com//" local="132122565660000000" remote="-1" Dst="-1" />
<file name="certificates.png" server="ftp.sffscorpion.com//" local="132122565660000000" remote="-1" Dst="-1" />
<file name="channels.png" server="ftp.sffscorpion.com//" local="132122565660000000" remote="-1" Dst="-1" />
<file name="downloads.png" server="ftp.sffscorpion.com//" local="132122565660000000" remote="-1" Dst="-1" />
<file name="featuredmovies.png" server="ftp.sffscorpion.com//" local="132122565660000000" remote="-1" Dst="-1" />
<file name="featuredtv.png" server="ftp.sffscorpion.com//" local="132122565660000000" remote="-1" Dst="-1" />
<file name="genres.png" server="ftp.sffscorpion.com//" local="132122565660000000" remote="-1" Dst="-1" />
<file name="highly-rated.png" server="ftp.sffscorpion.com//" local="132122565660000000" remote="-1" Dst="-1" />
<file name="imdb.png" server="ftp.sffscorpion.com//" local="132122565660000000" remote="-1" Dst="-1" />
<file name="in-theaters.png" server="ftp.sffscorpion.com//" local="132122565660000000" remote="-1" Dst="-1" />
<file name="languages.png" server="ftp.sffscorpion.com//" local="132122565660000000" remote="-1" Dst="-1" />
<file name="latest-movies.png" server="ftp.sffscorpion.com//" local="132122565660000000" remote="-1" Dst="-1" />
<file name="library_update.png" server="ftp.sffscorpion.com//" local="132122565660000000" remote="-1" Dst="-1" />
<file name="most-popular.png" server="ftp.sffscorpion.com//" local="132122565660000000" remote="-1" Dst="-1" />
<file name="most-voted.png" server="ftp.sffscorpion.com//" local="132122565660000000" remote="-1" Dst="-1" />
<file name="movies.png" server="ftp.sffscorpion.com//" local="132122565680000000" remote="-1" Dst="-1" />
<file name="mymovies.png" server="ftp.sffscorpion.com//" local="132122565680000000" remote="-1" Dst="-1" />
<file name="mytvshows.png" server="ftp.sffscorpion.com//" local="132122565680000000" remote="-1" Dst="-1" />
<file name="networks.png" server="ftp.sffscorpion.com//" local="132122565680000000" remote="-1" Dst="-1" />
<file name="new-movies.png" server="ftp.sffscorpion.com//" local="132122680660000000" remote="-1" Dst="-1" />
<file name="new-tvshows.png" server="ftp.sffscorpion.com//" local="132122565680000000" remote="-1" Dst="-1" />
<file name="oscar-winners.png" server="ftp.sffscorpion.com//" local="132122565680000000" remote="-1" Dst="-1" />
<file name="people-search.png" server="ftp.sffscorpion.com//" local="132122565680000000" remote="-1" Dst="-1" />
<file name="people-watching.png" server="ftp.sffscorpion.com//" local="132122565680000000" remote="-1" Dst="-1" />
<file name="people.png" server="ftp.sffscorpion.com//" local="132122565680000000" remote="-1" Dst="-1" />
<file name="poster.png" server="ftp.sffscorpion.com//" local="132122565680000000" remote="-1" Dst="-1" />
<file name="resolveurl.png" server="ftp.sffscorpion.com//" local="132122565680000000" remote="-1" Dst="-1" />
<file name="returning-tvshows.png" server="ftp.sffscorpion.com//" local="132122565680000000" remote="-1" Dst="-1" />
<file name="search.png" server="ftp.sffscorpion.com//" local="132122565680000000" remote="-1" Dst="-1" />
<file name="tools.png" server="ftp.sffscorpion.com//" local="132122565680000000" remote="-1" Dst="-1" />
<file name="trakt.png" server="ftp.sffscorpion.com//" local="132122565680000000" remote="-1" Dst="-1" />
<file name="trending.png" server="ftp.sffscorpion.com//" local="132122634530000000" remote="-1" Dst="-1" />
<file name="tvshows.png" server="ftp.sffscorpion.com//" local="132122565680000000" remote="-1" Dst="-1" />
<file name="userlists.png" server="ftp.sffscorpion.com//" local="132122565680000000" remote="-1" Dst="-1" />
<file name="years.png" server="ftp.sffscorpion.com//" local="132122565680000000" remote="-1" Dst="-1" />
</dwsync>