<?xml version="1.0" encoding="utf-8" ?>
<dwsync>
<file name="a&e.png" server="ftp.sffscorpion.com//" local="132122274770000000" remote="-1" Dst="-1" />
<file name="abc.png" server="ftp.sffscorpion.com//" local="132122274770000000" remote="-1" Dst="-1" />
<file name="adultswim.png" server="ftp.sffscorpion.com//" local="132122274770000000" remote="-1" Dst="-1" />
<file name="amazon.png" server="ftp.sffscorpion.com//" local="132122274770000000" remote="-1" Dst="-1" />
<file name="amc.png" server="ftp.sffscorpion.com//" local="132122274770000000" remote="-1" Dst="-1" />
<file name="animalplanet.png" server="ftp.sffscorpion.com//" local="132122274770000000" remote="-1" Dst="-1" />
<file name="bbc.png" server="ftp.sffscorpion.com//" local="132122274770000000" remote="-1" Dst="-1" />
<file name="bbc1.png" server="ftp.sffscorpion.com//" local="132122274770000000" remote="-1" Dst="-1" />
<file name="bbc2.png" server="ftp.sffscorpion.com//" local="132122274770000000" remote="-1" Dst="-1" />
<file name="bbc3.png" server="ftp.sffscorpion.com//" local="132122274770000000" remote="-1" Dst="-1" />
<file name="bbc4.png" server="ftp.sffscorpion.com//" local="132122274770000000" remote="-1" Dst="-1" />
<file name="boomerang.png" server="ftp.sffscorpion.com//" local="132122274770000000" remote="-1" Dst="-1" />
<file name="bravo.png" server="ftp.sffscorpion.com//" local="132122274770000000" remote="-1" Dst="-1" />
<file name="cartoon.png" server="ftp.sffscorpion.com//" local="132122274770000000" remote="-1" Dst="-1" />
<file name="cbs.png" server="ftp.sffscorpion.com//" local="132122274770000000" remote="-1" Dst="-1" />
<file name="cinemax.png" server="ftp.sffscorpion.com//" local="132122274770000000" remote="-1" Dst="-1" />
<file name="comedy.png" server="ftp.sffscorpion.com//" local="132122274770000000" remote="-1" Dst="-1" />
<file name="cw.png" server="ftp.sffscorpion.com//" local="132122274770000000" remote="-1" Dst="-1" />
<file name="cwseed.png" server="ftp.sffscorpion.com//" local="132122274770000000" remote="-1" Dst="-1" />
<file name="dc.png" server="ftp.sffscorpion.com//" local="132122274770000000" remote="-1" Dst="-1" />
<file name="discovery.png" server="ftp.sffscorpion.com//" local="132122274770000000" remote="-1" Dst="-1" />
<file name="discoveryfam.png" server="ftp.sffscorpion.com//" local="132122274770000000" remote="-1" Dst="-1" />
<file name="disney.png" server="ftp.sffscorpion.com//" local="132122274770000000" remote="-1" Dst="-1" />
<file name="disneyxd.png" server="ftp.sffscorpion.com//" local="132122274770000000" remote="-1" Dst="-1" />
<file name="diy.png" server="ftp.sffscorpion.com//" local="132122274770000000" remote="-1" Dst="-1" />
<file name="e!.png" server="ftp.sffscorpion.com//" local="132122274770000000" remote="-1" Dst="-1" />
<file name="food.png" server="ftp.sffscorpion.com//" local="132122274770000000" remote="-1" Dst="-1" />
<file name="fox.png" server="ftp.sffscorpion.com//" local="132122274770000000" remote="-1" Dst="-1" />
<file name="freeform.png" server="ftp.sffscorpion.com//" local="132122274770000000" remote="-1" Dst="-1" />
<file name="fx.png" server="ftp.sffscorpion.com//" local="132122274770000000" remote="-1" Dst="-1" />
<file name="fxx.png" server="ftp.sffscorpion.com//" local="132122274770000000" remote="-1" Dst="-1" />
<file name="hallmark.png" server="ftp.sffscorpion.com//" local="132122274770000000" remote="-1" Dst="-1" />
<file name="hbo.png" server="ftp.sffscorpion.com//" local="132122274770000000" remote="-1" Dst="-1" />
<file name="hgtv.png" server="ftp.sffscorpion.com//" local="132122274770000000" remote="-1" Dst="-1" />
<file name="history.png" server="ftp.sffscorpion.com//" local="132122274770000000" remote="-1" Dst="-1" />
<file name="hulu.png" server="ftp.sffscorpion.com//" local="132122274770000000" remote="-1" Dst="-1" />
<file name="id.png" server="ftp.sffscorpion.com//" local="132122274770000000" remote="-1" Dst="-1" />
<file name="ifc.png" server="ftp.sffscorpion.com//" local="132122274770000000" remote="-1" Dst="-1" />
<file name="lifetime.png" server="ftp.sffscorpion.com//" local="132122274770000000" remote="-1" Dst="-1" />
<file name="mtv.png" server="ftp.sffscorpion.com//" local="132122274770000000" remote="-1" Dst="-1" />
<file name="natgeo.png" server="ftp.sffscorpion.com//" local="132122274770000000" remote="-1" Dst="-1" />
<file name="nbc.png" server="ftp.sffscorpion.com//" local="132122274770000000" remote="-1" Dst="-1" />
<file name="netflix.png" server="ftp.sffscorpion.com//" local="132122274770000000" remote="-1" Dst="-1" />
<file name="nick.png" server="ftp.sffscorpion.com//" local="132122274770000000" remote="-1" Dst="-1" />
<file name="nickelodeon.png" server="ftp.sffscorpion.com//" local="132122274770000000" remote="-1" Dst="-1" />
<file name="nickjr.png" server="ftp.sffscorpion.com//" local="132122274770000000" remote="-1" Dst="-1" />
<file name="nicktoons.png" server="ftp.sffscorpion.com//" local="132122274770000000" remote="-1" Dst="-1" />
<file name="paramount.png" server="ftp.sffscorpion.com//" local="132122274770000000" remote="-1" Dst="-1" />
<file name="pbs.png" server="ftp.sffscorpion.com//" local="132122274770000000" remote="-1" Dst="-1" />
<file name="pbskids.png" server="ftp.sffscorpion.com//" local="132122274770000000" remote="-1" Dst="-1" />
<file name="science.png" server="ftp.sffscorpion.com//" local="132122274770000000" remote="-1" Dst="-1" />
<file name="showtime.png" server="ftp.sffscorpion.com//" local="132122274770000000" remote="-1" Dst="-1" />
<file name="starz.png" server="ftp.sffscorpion.com//" local="132122274770000000" remote="-1" Dst="-1" />
<file name="sundance.png" server="ftp.sffscorpion.com//" local="132122274770000000" remote="-1" Dst="-1" />
<file name="syfy.png" server="ftp.sffscorpion.com//" local="132122274770000000" remote="-1" Dst="-1" />
<file name="tbs.png" server="ftp.sffscorpion.com//" local="132122274770000000" remote="-1" Dst="-1" />
<file name="tlc.png" server="ftp.sffscorpion.com//" local="132122274770000000" remote="-1" Dst="-1" />
<file name="tnt.png" server="ftp.sffscorpion.com//" local="132122274770000000" remote="-1" Dst="-1" />
<file name="travel.png" server="ftp.sffscorpion.com//" local="132122274770000000" remote="-1" Dst="-1" />
<file name="tru.png" server="ftp.sffscorpion.com//" local="132122274770000000" remote="-1" Dst="-1" />
<file name="tvland.png" server="ftp.sffscorpion.com//" local="132122274770000000" remote="-1" Dst="-1" />
<file name="usa.png" server="ftp.sffscorpion.com//" local="132122274770000000" remote="-1" Dst="-1" />
<file name="vh1.png" server="ftp.sffscorpion.com//" local="132122274770000000" remote="-1" Dst="-1" />
<file name="vh1c.png" server="ftp.sffscorpion.com//" local="132122274770000000" remote="-1" Dst="-1" />
</dwsync>